lens/__init__.py
lens/actor/__init__.py
lens/actor/actor.py
lens/actor/boot.py
lens/actor/control.py
lens/actor/emitter.py
lens/actor/event.py
lens/actor/filepath.py
lens/actor/inner.py
lens/actor/outer.py
lens/actor/process.py
lens/actor/shepherd.py
lens/actor/stub.py
lens_interface-0.0.28.dist-info/LICENSE
lens_interface-0.0.28.dist-info/METADATA
lens_interface-0.0.28.dist-info/WHEEL
lens_interface-0.0.28.dist-info/top_level.txt
lens_interface-0.0.28.dist-info/RECORD
