Metadata-Version: 2.1
Name: lens-interface
Version: 0.0.28
Summary: UNKNOWN
Home-page: https://github.com/CovertLab/Lens
Author: Eran Agmon, Ryan Spangler
Author-email: eagmon@stanford.edu, spanglry@stanford.edu
License: MIT
Platform: UNKNOWN
Requires-Dist: confluent-kafka (==0.11.5)
Requires-Dist: numpy (==1.14.6)
Requires-Dist: pymongo (==3.6.1)
Requires-Dist: pytest (==4.6.5)
Requires-Dist: pytest-benchmark (==3.2.2)
